colour_hdri/__init__.py
colour_hdri/py.typed
colour_hdri/calibration/__init__.py
colour_hdri/calibration/absolute_luminance.py
colour_hdri/calibration/debevec1997.py
colour_hdri/calibration/tests/__init__.py
colour_hdri/calibration/tests/test_absolute_luminance.py
colour_hdri/calibration/tests/test_debevec1997.py
colour_hdri/distortion/__init__.py
colour_hdri/distortion/vignette.py
colour_hdri/distortion/tests/__init__.py
colour_hdri/distortion/tests/test_vignette.py
colour_hdri/examples/examples_absolute_luminance_calibration_and_photometric_exposure_conversion.ipynb
colour_hdri/examples/examples_adobe_dng_sdk_colour_processing.ipynb
colour_hdri/examples/examples_advanced_processing_with_an_input_device_transform.ipynb
colour_hdri/examples/examples_advanced_processing_with_the_nodegraph.ipynb
colour_hdri/examples/examples_global_tonemapping_operators.ipynb
colour_hdri/examples/examples_merge_from_ldr_files.ipynb
colour_hdri/examples/examples_merge_from_raw_files.ipynb
colour_hdri/examples/examples_merge_from_raw_files_using_rawpy.ipynb
colour_hdri/examples/examples_merge_from_raw_files_with_post_demosaicing.ipynb
colour_hdri/examples/examples_variance_minimization_light_probe_sampling.ipynb
colour_hdri/examples/examples_vignette_characterisation_and_correction.ipynb
colour_hdri/exposure/__init__.py
colour_hdri/exposure/common.py
colour_hdri/exposure/dsc.py
colour_hdri/exposure/tests/__init__.py
colour_hdri/exposure/tests/test_common.py
colour_hdri/exposure/tests/test_dsc.py
colour_hdri/generation/__init__.py
colour_hdri/generation/hdri.py
colour_hdri/generation/weighting_functions.py
colour_hdri/generation/tests/__init__.py
colour_hdri/generation/tests/test_hdri.py
colour_hdri/generation/tests/test_weighting_functions.py
colour_hdri/models/__init__.py
colour_hdri/models/dng.py
colour_hdri/models/rgb.py
colour_hdri/models/datasets/__init__.py
colour_hdri/models/datasets/dng.py
colour_hdri/models/tests/__init__.py
colour_hdri/models/tests/test_adobe_dng.py
colour_hdri-0.2.6.dist-info/METADATA
colour_hdri-0.2.6.dist-info/WHEEL
colour_hdri-0.2.6.dist-info/licenses/LICENSE
colour_hdri-0.2.6.dist-info/RECORD
