Metadata-Version: 2.4
Name: colour-hdri
Version: 0.2.6
Summary: HDRI processing algorithms for Python
Project-URL: Homepage, https://www.colour-science.org
Project-URL: Documentation, https://colour-hdri.readthedocs.org
Project-URL: Repository, https://github.com/colour-science/colour-hdri
Project-URL: Issues, https://github.com/colour-science/colour-hdri/issues
Project-URL: Changelog, https://github.com/colour-science/colour-hdri/releases
Author-email: Colour Developers <colour-developers@colour-science.org>
Maintainer-email: Colour Developers <colour-developers@colour-science.org>
License: BSD-3-Clause
License-File: LICENSE
Keywords: color,color-science,color-space,color-spaces,colorspace,colorspaces,colour,colour-science,colour-space,colour-spaces,colourspace,colourspaces,hdr,hdr-image,hdri,hdri-image,python,raw,tone-mapping,tonemapping
Classifier: Development Status :: 3 - Alpha
Classifier: Environment :: Console
Classifier: Intended Audience :: Developers
Classifier: Intended Audience :: Science/Research
Classifier: License :: OSI Approved
Classifier: Natural Language :: English
Classifier: Operating System :: OS Independent
Classifier: Programming Language :: Python :: 3
Classifier: Topic :: Scientific/Engineering
Classifier: Topic :: Software Development
Requires-Python: <3.15,>=3.11
Requires-Dist: colour-science>=0.4.7
Requires-Dist: imageio<3,>=2
Requires-Dist: numpy<3,>=2.0.0
Requires-Dist: scipy<2,>=1.13.0
Requires-Dist: typing-extensions<5,>=4
Provides-Extra: docs
Requires-Dist: biblib-simple; extra == 'docs'
Requires-Dist: pydata-sphinx-theme; extra == 'docs'
Requires-Dist: restructuredtext-lint; extra == 'docs'
Requires-Dist: sphinx; extra == 'docs'
Requires-Dist: sphinxcontrib-bibtex; extra == 'docs'
Provides-Extra: optional
Requires-Dist: colour-datasets>=0.2.7; extra == 'optional'
Requires-Dist: colour-demosaicing>=0.2.4; extra == 'optional'
Requires-Dist: lensfunpy<2; (python_version < '3.13') and extra == 'optional'
Requires-Dist: matplotlib>=3.9; extra == 'optional'
Requires-Dist: networkx<4,>=3.3; extra == 'optional'
Requires-Dist: opencv-python<5,>=4; extra == 'optional'
Requires-Dist: openimageio<4,>=3; extra == 'optional'
Requires-Dist: pydot<4,>=3; extra == 'optional'
Requires-Dist: rawpy<1; (python_version < '3.14') and extra == 'optional'
